emobpy/__init__.py
emobpy/__main__.py
emobpy/availability.py
emobpy/charging.py
emobpy/constants.py
emobpy/consumption.py
emobpy/database.py
emobpy/export.py
emobpy/functions.py
emobpy/init.py
emobpy/logger.py
emobpy/messages.py
emobpy/mobility.py
emobpy/plot.py
emobpy/tools.py
emobpy/data/ERA5-hourly-dew_point_temp.csv
emobpy/data/ERA5-hourly-mslp.csv
emobpy/data/ERA5-hourly-t2m.csv
emobpy/data/country_code_zones.json
emobpy/data/driving_cycles.csv
emobpy/data/driving_cycles.yaml
emobpy/data/evspecs.json
emobpy/data/motor_efficiency.csv
emobpy/data/base/Instructions.rst
emobpy/data/base/Step1Mobility.py
emobpy/data/base/Step2DrivingConsumption.py
emobpy/data/base/Step3GridAvailability.py
emobpy/data/base/Step4GridDemand.py
emobpy/data/base/Time-series_generation.ipynb
emobpy/data/base/Visualize_and_Export.ipynb
emobpy/data/base/config_files/DepartureDestinationTrip.csv
emobpy/data/base/config_files/DistanceDurationTrip.csv
emobpy/data/base/config_files/TripsPerDay.csv
emobpy/data/base/config_files/rules.yml
emobpy/data/base/config_files/seed.txt
emobpy/data/base/log/emobpy.log
emobpy/data/eg1/Instructions.rst
emobpy/data/eg1/eg1.ipynb
emobpy/data/eg1/config_files/DepartureDestinationTrip_Worker.csv
emobpy/data/eg1/config_files/DistanceDurationTrip.csv
emobpy/data/eg1/config_files/TripsPerDay.csv
emobpy/data/eg1/config_files/rules.yml
emobpy/data/eg1/config_files/seed.txt
emobpy/data/eg1/log/emobpy.log
emobpy/data/eg2/case_germany_mobility.txt
emobpy/data/eg2/config_files/DepartureDestinationTrip_Free.csv
emobpy/data/eg2/config_files/DepartureDestinationTrip_Worker.csv
emobpy/data/eg2/config_files/DistanceDurationTrip.csv
emobpy/data/eg2/config_files/TripsPerDay.csv
emobpy/data/eg2/config_files/rules.yml
emobpy/data/eg2/config_files/seed.txt
emobpy/data/eg2/log/emobpy.log
emobpy/data/eg3/Step1Mobility.py
emobpy/data/eg3/Step2DrivingConsumption.py
emobpy/data/eg3/Step3GridAvailability.py
emobpy/data/eg3/Step4GridDemand.py
emobpy/data/eg3/Visualize_and_Export.ipynb
emobpy-0.6.2.dist-info/LICENSE
emobpy-0.6.2.dist-info/METADATA
emobpy-0.6.2.dist-info/WHEEL
emobpy-0.6.2.dist-info/entry_points.txt
emobpy-0.6.2.dist-info/top_level.txt
emobpy-0.6.2.dist-info/RECORD
