Metadata-Version: 2.1
Name: emobpy
Version: 0.6.2
Summary: Time series for battery electric vehicles modeling
Home-page: https://gitlab.com/diw-evu/emobpy/emobpy
Author: Carlos Gaete-Morales
Author-email: cdgaete@gmail.com
Maintainer: v0.5.7: Lukas Trippe, v0.6.0: Benedikt Tepe
License: UNKNOWN
Platform: UNKNOWN
Classifier: Intended Audience :: End Users/Desktop
Classifier: Intended Audience :: Developers
Classifier: Intended Audience :: Science/Research
Classifier: License :: OSI Approved :: MIT License
Classifier: Operating System :: MacOS :: MacOS X
Classifier: Operating System :: Microsoft :: Windows
Classifier: Operating System :: POSIX
Classifier: Programming Language :: Python
Classifier: Programming Language :: Python :: 3
Classifier: Programming Language :: Python :: 3.6
Classifier: Programming Language :: Python :: 3.7
Classifier: Programming Language :: Python :: 3.8
Classifier: Programming Language :: Python :: 3.9
Classifier: Topic :: Scientific/Engineering :: Information Analysis
Classifier: Topic :: Scientific/Engineering :: Mathematics
Classifier: Topic :: Scientific/Engineering :: Visualization
License-File: LICENSE
Requires-Dist: appdirs
Requires-Dist: plotly
Requires-Dist: cufflinks
Requires-Dist: zenodo-get
Requires-Dist: pyyaml
Requires-Dist: pandas
Requires-Dist: wget
Requires-Dist: numba
